lyngdorf/__init__.py
lyngdorf/api.py
lyngdorf/base.py
lyngdorf/const.py
lyngdorf/device.py
lyngdorf/exceptions.py
lyngdorf-0.5.0.dist-info/METADATA
lyngdorf-0.5.0.dist-info/WHEEL
lyngdorf-0.5.0.dist-info/RECORD
