Metadata-Version: 2.4
Name: lyngdorf
Version: 0.5.0
Summary: Library to control a Lyngdorf A/V processor
License: MIT
Author: Alex Fishlock
Author-email: alex.fishlock@racingjag.com
Requires-Python: >=3.11,<4.0
Classifier: Development Status :: 4 - Beta
Classifier: Intended Audience :: Developers
Classifier: License :: OSI Approved :: MIT License
Classifier: Operating System :: OS Independent
Classifier: Programming Language :: Python :: 3
Classifier: Programming Language :: Python :: 3.11
Classifier: Programming Language :: Python :: 3.12
Classifier: Programming Language :: Python :: 3.13
Classifier: Programming Language :: Python :: 3.14
Requires-Dist: attrs (>=21.0.0)
Project-URL: Homepage, https://github.com/fishloa/lyngdorf
Project-URL: Issues, https://github.com/fishloa/lyngdorf/issues
